LICENSE
MANIFEST.in
README.rst
setup.py
examples/__init__.py
examples/quickstart.py
examples/simple_space_heating_mpc.py
mpcpy/__init__.py
mpcpy/__version__.py
mpcpy/control.py
mpcpy/disturbances.py
mpcpy/emulator.py
mpcpy/mpc.py
mpcpy/prediction.py
mpcpy/stateestimation.py
mpcpy.egg-info/PKG-INFO
mpcpy.egg-info/SOURCES.txt
mpcpy.egg-info/dependency_links.txt
mpcpy.egg-info/requires.txt
mpcpy.egg-info/top_level.txt
tests/__init__.py
tests/all.py
tests/boundaryconditions.py
tests/emulator.py
tests/examples.py
tests/prediction.py
tests/stateestimation.py