Metadata-Version: 1.1
Name: mpcpy
Version: 0.3.0
Summary: A package to run MPC, moving horizon simulations in Python.
Home-page: https://github.com/BrechtBa/mpcpy
Author: Brecht Baeten
Author-email: brecht.baeten@gmail.com
License: GPLv3
Platform: UNKNOWN
Classifier: Programming Language :: Python :: 2.7
